cebeo_client/__init__.py
cebeo_client/client.py
cebeo_client/exceptions.py
cebeo_client/models.py
cebeo_client-0.4.0.dist-info/METADATA
cebeo_client-0.4.0.dist-info/WHEEL
cebeo_client-0.4.0.dist-info/licenses/LICENSE
cebeo_client-0.4.0.dist-info/RECORD
